ColorCorrectionML/ColorCorrectionML.py
ColorCorrectionML/__init__.py
ColorCorrectionML/reference_values.py
colorcorrectionML-0.0.2.1.dist-info/LICENSE.md
colorcorrectionML-0.0.2.1.dist-info/METADATA
colorcorrectionML-0.0.2.1.dist-info/WHEEL
colorcorrectionML-0.0.2.1.dist-info/top_level.txt
colorcorrectionML-0.0.2.1.dist-info/RECORD
