Metadata-Version: 2.1
Name: colorcorrectionML
Version: 0.0.2.1
Summary: Do color correction of images using machine learning.
Home-page: https://github.com/collinswakholi/ML_ColorCorrection_tool
Author: Collins Wakholi
Classifier: Programming Language :: Python :: 3
Classifier: Operating System :: OS Independent
Requires-Python: >=3.7
License-File: LICENSE.md
Requires-Dist: scikit-learn
Requires-Dist: numpy
Requires-Dist: matplotlib
Requires-Dist: opencv-python
Requires-Dist: networkx
Requires-Dist: colour-science
Requires-Dist: dask
